bsx_py_beta/__init__.py
bsx_py_beta/client/__init__.py
bsx_py_beta/client/rest/__init__.py
bsx_py_beta/client/rest/account/__init__.py
bsx_py_beta/client/rest/account/client.py
bsx_py_beta/client/rest/account/types.py
bsx_py_beta/client/rest/auth/__init__.py
bsx_py_beta/client/rest/auth/client.py
bsx_py_beta/client/rest/auth/types.py
bsx_py_beta/client/rest/base.py
bsx_py_beta/client/rest/market/__init__.py
bsx_py_beta/client/rest/market/client.py
bsx_py_beta/client/rest/market/types.py
bsx_py_beta/common/__init__.py
bsx_py_beta/common/acc_info.py
bsx_py_beta/common/exception.py
bsx_py_beta/common/lock.py
bsx_py_beta/common/types/__init__.py
bsx_py_beta/common/types/account.py
bsx_py_beta/common/types/auth.py
bsx_py_beta/common/types/base.py
bsx_py_beta/common/types/market.py
bsx_py_beta/helper/__init__.py
bsx_py_beta/helper/acc_storage.py
bsx_py_beta/helper/api_key_base_manager.py
bsx_py_beta/helper/base.py
bsx_py_beta/helper/secret_base_manager.py
bsx_py_beta/instance.py
bsx_sdk_beta-0.0.1b11.dist-info/METADATA
bsx_sdk_beta-0.0.1b11.dist-info/WHEEL
bsx_sdk_beta-0.0.1b11.dist-info/RECORD
